LICENSE
MANIFEST.in
pyproject.toml
requirements.txt
setup.py
poismf/__init__.py
poismf/cfuns_double.pyx
poismf/cfuns_float.pyx
poismf/poismf_c_wrapper.pxi
poismf.egg-info/PKG-INFO
poismf.egg-info/SOURCES.txt
poismf.egg-info/dependency_links.txt
poismf.egg-info/requires.txt
poismf.egg-info/top_level.txt
src/nonnegcg.c
src/poismf.c
src/poismf.h
src/pred.c
src/tnc.c
src/tnc.h
src/topN.c