Metadata-Version: 2.1
Name: poismf
Version: 0.4.0
Summary: Fast and memory-efficient Poisson factorization for sparse count matrices
Home-page: https://github.com/david-cortes/poismf
Author: David Cortes
Author-email: david.cortes.rivera@gmail.com
License: UNKNOWN
Platform: UNKNOWN
License-File: LICENSE
